package_mikezhou_talk/__init__.py
package_mikezhou_talk/main.py
package_mikezhou_talk-1.0.0.dist-info/LICENSE
package_mikezhou_talk-1.0.0.dist-info/METADATA
package_mikezhou_talk-1.0.0.dist-info/WHEEL
package_mikezhou_talk-1.0.0.dist-info/top_level.txt
package_mikezhou_talk-1.0.0.dist-info/RECORD
