Metadata-Version: 2.1
Name: package-mikezhou-talk
Version: 1.0.0
Summary: A small example package
Home-page: https://mp.weixin.qq.com/s/9FQ-Tun5FbpBepBAsdY62w
Author: mikezhou_talk
Author-email: 762357658@qq.com
License: BSD License
Platform: all
Classifier: Intended Audience :: Developers
Classifier: Operating System :: OS Independent
Classifier: Natural Language :: Chinese (Simplified)
Classifier: Programming Language :: Python
Classifier: Programming Language :: Python :: 2
Classifier: Programming Language :: Python :: 2.7
Classifier: Programming Language :: Python :: 3
Classifier: Programming Language :: Python :: 3.5
Classifier: Programming Language :: Python :: 3.6
Classifier: Programming Language :: Python :: 3.7
Classifier: Programming Language :: Python :: 3.8
Classifier: Topic :: Software Development :: Libraries
